liteyukibot_plugin_antidislink-0.1.0.dist-info/METADATA
liteyukibot_plugin_antidislink-0.1.0.dist-info/WHEEL
liteyukibot_plugin_antidislink/__init__.py
liteyukibot_plugin_antidislink-0.1.0.dist-info/RECORD
