Metadata-Version: 2.1
Name: liteyukibot-plugin-antidislink
Version: 0.1.0
Summary: 防止群友断联化
Author-Email: snowykami <snowykami@outlook.com>
License: MIT & LSO
Requires-Python: >=3.10
Requires-Dist: liteyukibot>=6.3.9
